wagtail_flexible_forms/__init__.py
wagtail_flexible_forms/blocks.py
wagtail_flexible_forms/edit_handlers.py
wagtail_flexible_forms/models.py
wagtail_flexible_forms/wagtail_hooks.py
wagtail_flexible_forms-2.1.0.dist-info/licenses/LICENSE.txt
wagtail_flexible_forms-2.1.0.dist-info/METADATA
wagtail_flexible_forms-2.1.0.dist-info/WHEEL
wagtail_flexible_forms-2.1.0.dist-info/top_level.txt
wagtail_flexible_forms-2.1.0.dist-info/RECORD
