Metadata-Version: 2.4
Name: wagtail-flexible-forms
Version: 2.1.0
Summary: Wagtail StreamField-based form builder.
Author: Bertrand Bordage
Author-email: CodeRed LLC <info@coderedcorp.com>
License: BSD 3-Clause License
Project-URL: Source, https://github.com/coderedcorp/wagtail-flexible-forms
Classifier: Intended Audience :: Developers
Classifier: License :: OSI Approved :: BSD License
Classifier: Natural Language :: English
Classifier: Operating System :: OS Independent
Classifier: Programming Language :: Python :: 3
Classifier: Programming Language :: Python :: 3 :: Only
Classifier: Framework :: Django
Classifier: Framework :: Wagtail
Classifier: Framework :: Wagtail :: 6
Classifier: Framework :: Wagtail :: 7
Requires-Python: >=3.9
License-File: LICENSE.txt
Requires-Dist: wagtail<8,>=6
Dynamic: license-file
